cgir/__init__.py
cgir/cli.py
cgir/infrared.py
cgir-1.2.dist-info/LICENSE
cgir-1.2.dist-info/METADATA
cgir-1.2.dist-info/WHEEL
cgir-1.2.dist-info/entry_points.txt
cgir-1.2.dist-info/top_level.txt
cgir-1.2.dist-info/RECORD
